nomad_media_cli/__init__.py
nomad_media_cli/cli.py
nomad_media_cli/commands/__init__.py
nomad_media_cli/commands/admin/__init__.py
nomad_media_cli/commands/admin/asset_upload/__init__.py
nomad_media_cli/commands/admin/asset_upload/upload_assets.py
nomad_media_cli/commands/admin/config/__init__.py
nomad_media_cli/commands/admin/config/clear_server_cache.py
nomad_media_cli/commands/admin/config/get_config.py
nomad_media_cli/commands/admin/config/get_server_time.py
nomad_media_cli/commands/admin/content/__init__.py
nomad_media_cli/commands/admin/content/create_content.py
nomad_media_cli/commands/admin/content/deactivate_content_user_track.py
nomad_media_cli/commands/admin/content/delete_content.py
nomad_media_cli/commands/admin/content/get_content.py
nomad_media_cli/commands/admin/content/get_content_user_track.py
nomad_media_cli/commands/admin/content/get_content_user_track_touch.py
nomad_media_cli/commands/admin/content/update_content.py
nomad_media_cli/commands/admin/content_definition/__init__.py
nomad_media_cli/commands/admin/content_definition/create_content_definition.py
nomad_media_cli/commands/admin/content_definition/get_content_definition.py
nomad_media_cli/commands/admin/content_definition/get_content_definitions.py
nomad_media_cli/commands/admin/content_definition/update_content_definition.py
nomad_media_cli/commands/admin/event/__init__.py
nomad_media_cli/commands/admin/event/add_live_schedule_to_event.py
nomad_media_cli/commands/admin/event/create_update_event.py
nomad_media_cli/commands/admin/event/delete_event.py
nomad_media_cli/commands/admin/event/extent_live_schedule.py
nomad_media_cli/commands/admin/event/get_live_schedule.py
nomad_media_cli/commands/admin/event/start_live_schedule.py
nomad_media_cli/commands/admin/event/stop_live_schedule.py
nomad_media_cli/commands/admin/live_channel/__init__.py
nomad_media_cli/commands/admin/live_channel/clip_live_channel.py
nomad_media_cli/commands/admin/live_channel/create_live_channel.py
nomad_media_cli-0.1.2.dist-info/METADATA
nomad_media_cli-0.1.2.dist-info/WHEEL
nomad_media_cli-0.1.2.dist-info/entry_points.txt
nomad_media_cli-0.1.2.dist-info/top_level.txt
nomad_media_cli-0.1.2.dist-info/RECORD
