Metadata-Version: 2.2
Name: nomad_media_cli
Version: 0.1.2
Summary: Nomad Media CLI
Author: Nomad Media
Classifier: Programming Language :: Python :: 3.12
Requires-Python: >=3.12
Requires-Dist: click
Requires-Dist: platformdirs
Requires-Dist: nomad-media-pip==0.1.4
Dynamic: author
Dynamic: classifier
Dynamic: requires-dist
Dynamic: requires-python
Dynamic: summary
